{
  "articles": [
    {
      "title": "Brazilian exchange Mercado Bitcoin outlines 6 crypto trends shaping markets in 2026",
      "link": "https://www.coindesk.com/business/2026/01/10/brazilian-exchange-mercado-bitcoin-outlines-6-crypto-trends-shaping-markets-in-2026",
      "description": "The stablecoin sector is expected to grow to $500 billion, while altcoin ETFs are projected to reach $10 billion, driven by regulatory clarity and adoption.",
      "pubDate": "2026-01-10T15:31:54.000Z",
      "source": "CoinDesk",
      "sourceKey": "coindesk",
      "category": "general",
      "timeAgo": "34m ago"
    },
    {
      "title": "Institutions know a “good” exchange is built for failure",
      "link": "https://www.coindesk.com/opinion/2026/01/10/institutions-know-a-good-exchange-is-built-for-failure",
      "description": "A platform's onboarding polish should not be confused for its ability to execute trades and handle immense volumes, argues Bridgeport co-founder and CCO Chris Soriano.",
      "pubDate": "2026-01-10T15:00:00.000Z",
      "source": "CoinDesk",
      "sourceKey": "coindesk",
      "category": "general",
      "timeAgo": "1h ago"
    }
  ],
  "totalCount": 2,
  "sources": [
    "CoinDesk"
  ],
  "fetchedAt": "2026-01-10T16:06:17.108Z",
  "cachedAt": "2026-01-10T16:05:54.000Z",
  "source": "failsafe-cache"
}
